PyMoosh/__init__.py
PyMoosh/alt_methods.py
PyMoosh/anisotropic.py
PyMoosh/classes.py
PyMoosh/core.py
PyMoosh/grads.py
PyMoosh/green.py
PyMoosh/incoherent.py
PyMoosh/incoherent_vectorized.py
PyMoosh/models.py
PyMoosh/modes.py
PyMoosh/non_local.py
PyMoosh/optim_algo.py
PyMoosh/photo.py
PyMoosh/vectorized.py
PyMoosh/data/material_data.json
PyMoosh/data/solar.json
pymoosh-4.0.dist-info/LICENSE.txt
pymoosh-4.0.dist-info/METADATA
pymoosh-4.0.dist-info/WHEEL
pymoosh-4.0.dist-info/top_level.txt
pymoosh-4.0.dist-info/RECORD
