Metadata-Version: 2.1
Name: PyMoosh
Version: 4.0
Summary: A numerical swiss army knife for computing and optimizing the optical response of multilayered structures.
Home-page: https://github.com/AnMoreau/PyMoosh
Author: Antoine Moreau and Denis Langevin
Author-email: denis.langevin@univ-amu.fr
License: MIT
Keywords: Moosh,Maxwell,Optics,Multilayers,Plasmonics,Photovoltaics
License-File: LICENSE.txt
Requires-Dist: numpy
Requires-Dist: matplotlib
Requires-Dist: scipy
